{
  "lastSync": "2026/03/27 15:17",
  "finance": [
    {
      "time": "03/27 09:55",
      "title": "【Yahoo早盤】中東戰事混亂！台股跌逾600點 股市名師蔡明翰：現在最好「先觀望」",
      "summary": "&nbsp;&nbsp;Yahoo股市"
    },
    {
      "time": "03/27 08:47",
      "title": "東京股市崩跌！日經指數大跌逾900點 川普「這句話」掀市場恐慌",
      "summary": "&nbsp;&nbsp;自由財經"
    },
    {
      "time": "03/27 09:18",
      "title": "台股又失守3萬3！中東戰爭短期難停火 大盤一度跌近600點",
      "summary": "&nbsp;&nbsp;Yahoo股市"
    },
    {
      "time": "03/27 12:04",
      "title": "【Hot台股】記憶體青筍筍...網喊「沒腰斬都是高點」 分析師搖頭示警：快逃",
      "summary": "&nbsp;&nbsp;Yahoo股市"
    }
  ],
  "langtech": [
    {
      "time": "03/27 14:29",
      "title": "當梵谷喝起珍奶 亞洲大學讓生成式AI走進高教現場",
      "summary": "&nbsp;&nbsp;中央社 CNA"
    },
    {
      "time": "03/27 10:50",
      "title": "生成式AI升級具身智慧 氮化鎵技術驅動電源轉型",
      "summary": "&nbsp;&nbsp;mem.com.tw"
    },
    {
      "time": "03/27 07:56",
      "title": "輝達Blackwell AI晶片全球出貨 揭開工業級AI新紀元",
      "summary": "&nbsp;&nbsp;sunmedia.tw"
    },
    {
      "time": "03/25 10:06",
      "title": "文科省公布高中2、3年級教科書檢定＝生成式AI多樣呈現、大半刊載QR Code",
      "summary": "&nbsp;&nbsp;nippon.com"
    }
  ],
  "migration": [
    {
      "time": "03/27 14:57",
      "title": "體驗優質校園學習氛圍 日本台灣留學支援中心師生至長榮大學參訪",
      "summary": "&nbsp;&nbsp;蕃新聞"
    },
    {
      "time": "03/23 16:07",
      "title": "簽證門檻與成本攀升 印度學生留學重心轉向歐亞",
      "summary": "&nbsp;&nbsp;Yahoo股市"
    },
    {
      "time": "03/26 08:42",
      "title": "出國留學有何新變",
      "summary": "&nbsp;&nbsp;人民网教育"
    },
    {
      "time": "03/26 14:15",
      "title": "2次留學中國 美國女子：不須背學債 畢業更有出路",
      "summary": "&nbsp;&nbsp;世界新聞網"
    }
  ]
}